Workbook

Sheet Parametros
A1: PARÁMETROS MERCADO LIBRE — Embalog Packaging
A2: Fuente: API ML /sites/MLA/listing_prices (categoría MLA405117, tipo Clásica) consultada el 16-jul-2026. Los valores CAMBIAN seguido: re-verificar cada tanto.
A4: IVA | B4: 0.21 | C4: Alicuota general. Los precios de Odoo son netos; ML publica precio final con IVA.
A5: Comisión ML Clásica (%) | B5: 0.1532085 | C5: Medida vía API el 16-jul-2026 para tu categoría.
A6: Umbral tramo 1 → 2 del costo fijo ($) | B6: 16000 | C6: SUPUESTO: la API mostró $1.250 hasta $15.000 y $2.505 en $20.000; el corte exacto no es público.
A7: Umbral tramo 2 → 3 del costo fijo ($) | B7: 25000 | C7: SUPUESTO: la API mostró $2.505 en $20.000 y $3.005 en $30.000.
A8: Umbral SIN costo fijo ($) | B8: 40000 | C8: Verificado: a $40.000+ el costo fijo es $0. LA CLAVE: publicar packs arriba de este valor.
A9: Costo fijo tramo 1 ($) | B9: 1250 | C9: Precio final hasta el umbral tramo 1.
A10: Costo fijo tramo 2 ($) | B10: 2505 | C10: Entre umbral 1 y 2.
A11: Costo fijo tramo 3 ($) | B11: 3005 | C11: Entre umbral 2 y el umbral sin costo fijo.
A12: Envío estimado por pack ($) | B12: 29860 | C12: EDITABLE. Costo real Mercado Envios (API 16-jul-2026), tramo minimo (hasta 15 kg facturable): $29.860. Tramos: 15-18,5kg $35.660 | 18,5-23kg $42.840. Las filas ya cargadas tienen su envio real pisado en la columna N.
A13: Buffer financiación / cuotas (%) | B13: 0 | C13: EDITABLE. En 0 porque NO se ofrecen cuotas sin interes. Si activas cuotas en ML, poner el % correspondiente y recalcular precios (bajan ~5-7 puntos de margen).
A14: Margen objetivo sobre costo (%) | B14: 0.28 | C14: EDITABLE. Ganancia neta buscada sobre el costo del pack. 25% ≈ tu precio actual de la caja x36.
A16: Celdas AMARILLAS = las tocás vos. El resto no hace falta tocarlo.
A18: PLAN HIBRIDO aplicado 17-jul-2026: formato chico <$40k (envio a cargo del comprador) + 3 banderas con envio gratis (reputacion).

Sheet Calculadora
A1: CALCULADORA DE PRECIOS PARA MERCADO LIBRE — packs para esquivar el costo fijo
A2: AMARILLO = editable (Unid/pack, Margen, Precio a publicar) · AZUL = dato de Odoo (16-jul-2026) · resto = fórmulas. El pack sugerido apunta a superar $42.000 finales (sin costo fijo de ML): AJUSTALO al múltiplo de tu caja cerrada.
A3: Id Odoo | B3: Código | C3: Producto | D3: Costo unit. neto $ | E3: Precio Odoo unit. neto $ | F3: Stock | G3: Unid. por pack | H3: Costo pack neto $ | I3: Margen objetivo % | J3: Precio base $ (s/costo fijo) | K3: Precio ML sugerido $ | L3: PRECIO A PUBLICAR $ (IVA incl.) | M3: Comisión ML $ | N3: Envío $ | O3: Financiación $ | P3: Recibís $ | Q3: Recibís neto s/IVA $ | R3: Ganancia $ | S3: Margen real % | T3: Estado | U3: Precio unit. equiv. neto $ | V3: Vs precio Odoo %
A4: 897 | B4: EP1032 | C4: Cinta De Embalaje Transparente 24 Mm x 45 Mts | D4: 253 | E4: 590 | F4: 0 | G4: 72 | H4: =D4*G4 | I4: =Parametros!$B$14 | J4: =((1+Parametros!$B$4)*H4*(1+I4)+Parametros!$B$12)/(1-Parametros!$B$5-Parametros!$B$13) | K4: =((1+Parametros!$B$4)*H4*(1+I4)+Parametros!$B$12+IF(J4>=Parametros!$B$8,0,IF(J4>=Parametros!$B$7,Parametros!$B$11,IF(J4>=Parametros!$B$6,Parametros!$B$10,Parametros!$B$9))))/(1-Parametros!$B$5-Parametros!$B$13) | L4: 30900 | M4: =L4*Parametros!$B$5+IF(L4>=Parametros!$B$8,0,IF(L4>=Parametros!$B$7,Parametros!$B$11,IF(L4>=Parametros!$B$6,Parametros!$B$10,Parametros!$B$9))) | N4: 0 | O4: =L4*Parametros!$B$13 | P4: =L4-M4-N4-O4 | Q4: =P4/(1+Parametros!$B$4) | R4: =Q4-H4 | S4: =IF(H4=0,0,R4/H4) | T4: =IF(L4<Parametros!$B$8,"PAGA COSTO FIJO",IF(S4>=I4,"OK","AJUSTAR")) | U4: =L4/(1+Parametros!$B$4)/G4 | V4: =IF(E4=0,0,U4/E4-1) | W4: Formato chico (envío a cargo del comprador)
A5: 900 | B5: EP1029 | C5: Cinta De Embalaje Transparente 48 Mm x 90 Mts [NO PUBLICAR: duplicado de fila 6] | D5: 925 | E5: 1419 | F5: 1 | G5: 36 | H5: =D5*G5 | I5: =Parametros!$B$14 | J5: =((1+Parametros!$B$4)*H5*(1+I5)+Parametros!$B$12)/(1-Parametros!$B$5-Parametros!$B$13) | K5: =((1+Parametros!$B$4)*H5*(1+I5)+Parametros!$B$12+IF(J5>=Parametros!$B$8,0,IF(J5>=Parametros!$B$7,Parametros!$B$11,IF(J5>=Parametros!$B$6,Parametros!$B$10,Parametros!$B$9))))/(1-Parametros!$B$5-Parametros!$B$13) | L5: =CEILING(K5,500) | M5: =L5*Parametros!$B$5+IF(L5>=Parametros!$B$8,0,IF(L5>=Parametros!$B$7,Parametros!$B$11,IF(L5>=Parametros!$B$6,Parametros!$B$10,Parametros!$B$9))) | N5: =Parametros!$B$12 | O5: =L5*Parametros!$B$13 | P5: =L5-M5-N5-O5 | Q5: =P5/(1+Parametros!$B$4) | R5: =Q5-H5 | S5: =IF(H5=0,0,R5/H5) | T5: =IF(L5<Parametros!$B$8,"PAGA COSTO FIJO",IF(S5>=I5,"OK","AJUSTAR")) | U5: =L5/(1+Parametros!$B$4)/G5 | V5: =IF(E5=0,0,U5/E5-1)
A6: 1005 | C6: Cinta De Embalaje Transp. 48 Mm x 90 Mts (Caja de 36 unid) — YA PUBLICADO EN ML | D6: 33315 | E6: 60230 | F6: 0 | G6: 1 | H6: =D6*G6 | I6: =Parametros!$B$14 | J6: =((1+Parametros!$B$4)*H6*(1+I6)+Parametros!$B$12)/(1-Parametros!$B$5-Parametros!$B$13) | K6: =((1+Parametros!$B$4)*H6*(1+I6)+Parametros!$B$12+IF(J6>=Parametros!$B$8,0,IF(J6>=Parametros!$B$7,Parametros!$B$11,IF(J6>=Parametros!$B$6,Parametros!$B$10,Parametros!$B$9))))/(1-Parametros!$B$5-Parametros!$B$13) | L6: 75500 | M6: =L6*Parametros!$B$5+IF(L6>=Parametros!$B$8,0,IF(L6>=Parametros!$B$7,Parametros!$B$11,IF(L6>=Parametros!$B$6,Parametros!$B$10,Parametros!$B$9))) | N6: 29860 | O6: =L6*Parametros!$B$13 | P6: =L6-M6-N6-O6 | Q6: =P6/(1+Parametros!$B$4) | R6: =Q6-H6 | S6: =IF(H6=0,0,R6/H6) | T6: =IF(L6<Parametros!$B$8,"PAGA COSTO FIJO",IF(S6>=I6,"OK","AJUSTAR")) | U6: =L6/(1+Parametros!$B$4)/G6 | V6: =IF(E6=0,0,U6/E6-1) | W6: BANDERA (envío gratis)
A7: 906 | B7: EP1059 | C7: Cinta De Papel Rapifix 48 Mm x 50 Mts Con Envase | D7: 4552 | E7: 6463 | F7: 0 | G7: 18 | H7: =D7*G7 | I7: =Parametros!$B$14 | J7: =((1+Parametros!$B$4)*H7*(1+I7)+Parametros!$B$12)/(1-Parametros!$B$5-Parametros!$B$13) | K7: =((1+Parametros!$B$4)*H7*(1+I7)+Parametros!$B$12+IF(J7>=Parametros!$B$8,0,IF(J7>=Parametros!$B$7,Parametros!$B$11,IF(J7>=Parametros!$B$6,Parametros!$B$10,Parametros!$B$9))))/(1-Parametros!$B$5-Parametros!$B$13) | L7: 33900 | M7: =L7*Parametros!$B$5+IF(L7>=Parametros!$B$8,0,IF(L7>=Parametros!$B$7,Parametros!$B$11,IF(L7>=Parametros!$B$6,Parametros!$B$10,Parametros!$B$9))) | N7: 0 | O7: =L7*Parametros!$B$13 | P7: =L7-M7-N7-O7 | Q7: =P7/(1+Parametros!$B$4) | R7: =Q7-H7 | S7: =IF(H7=0,0,R7/H7) | T7: =IF(L7<Parametros!$B$8,"PAGA COSTO FIJO",IF(S7>=I7,"OK","AJUSTAR")) | U7: =L7/(1+Parametros!$B$4)/G7 | V7: =IF(E7=0,0,U7/E7-1) | W7: Formato chico (envío a cargo del comprador)
A8: 935 | B8: EP1020 | C8: Film Alimenticio 45 Cm x 600 Mts | D8: 15146 | E8: 29449 | F8: 16 | G8: 4 | H8: =D8*G8 | I8: =Parametros!$B$14 | J8: =((1+Parametros!$B$4)*H8*(1+I8)+Parametros!$B$12)/(1-Parametros!$B$5-Parametros!$B$13) | K8: =((1+Parametros!$B$4)*H8*(1+I8)+Parametros!$B$12+IF(J8>=Parametros!$B$8,0,IF(J8>=Parametros!$B$7,Parametros!$B$11,IF(J8>=Parametros!$B$6,Parametros!$B$10,Parametros!$B$9))))/(1-Parametros!$B$5-Parametros!$B$13) | L8: 29000 | M8: =L8*Parametros!$B$5+IF(L8>=Parametros!$B$8,0,IF(L8>=Parametros!$B$7,Parametros!$B$11,IF(L8>=Parametros!$B$6,Parametros!$B$10,Parametros!$B$9))) | N8: 0 | O8: =L8*Parametros!$B$13 | P8: =L8-M8-N8-O8 | Q8: =P8/(1+Parametros!$B$4) | R8: =Q8-H8 | S8: =IF(H8=0,0,R8/H8) | T8: =IF(L8<Parametros!$B$8,"PAGA COSTO FIJO",IF(S8>=I8,"OK","AJUSTAR")) | U8: =L8/(1+Parametros!$B$4)/G8 | V8: =IF(E8=0,0,U8/E8-1) | W8: Formato chico (envío a cargo del comprador)
A9: 917 | B9: EP1048 | C9: Film Stretch Automático Transparente 50 Cm 7.5 Kg | D9: 2838 | E9: 4524 | F9: 0 | G9: 22.5 | H9: =D9*G9 | I9: =Parametros!$B$14 | J9: =((1+Parametros!$B$4)*H9*(1+I9)+Parametros!$B$12)/(1-Parametros!$B$5-Parametros!$B$13) | K9: =((1+Parametros!$B$4)*H9*(1+I9)+Parametros!$B$12+IF(J9>=Parametros!$B$8,0,IF(J9>=Parametros!$B$7,Parametros!$B$11,IF(J9>=Parametros!$B$6,Parametros!$B$10,Parametros!$B$9))))/(1-Parametros!$B$5-Parametros!$B$13) | L9: 39500 | M9: =L9*Parametros!$B$5+IF(L9>=Parametros!$B$8,0,IF(L9>=Parametros!$B$7,Parametros!$B$11,IF(L9>=Parametros!$B$6,Parametros!$B$10,Parametros!$B$9))) | N9: 0 | O9: =L9*Parametros!$B$13 | P9: =L9-M9-N9-O9 | Q9: =P9/(1+Parametros!$B$4) | R9: =Q9-H9 | S9: =IF(H9=0,0,R9/H9) | T9: =IF(L9<Parametros!$B$8,"PAGA COSTO FIJO",IF(S9>=I9,"OK","AJUSTAR")) | U9: =L9/(1+Parametros!$B$4)/G9 | V9: =IF(E9=0,0,U9/E9-1) | W9: Formato chico (envío a cargo del comprador)
A10: 923 | B10: EP1016 | C10: Film Stretch Manual Negro 10 Cm 0.5 Kg x Unidad | D10: 1686 | E10: 3203 | F10: 0 | G10: 25 | H10: =D10*G10 | I10: =Parametros!$B$14 | J10: =((1+Parametros!$B$4)*H10*(1+I10)+Parametros!$B$12)/(1-Parametros!$B$5-Parametros!$B$13) | K10: =((1+Parametros!$B$4)*H10*(1+I10)+Parametros!$B$12+IF(J10>=Parametros!$B$8,0,IF(J10>=Parametros!$B$7,Parametros!$B$11,IF(J10>=Parametros!$B$6,Parametros!$B$10,Parametros!$B$9))))/(1-Parametros!$B$5-Parametros!$B$13) | L10: 37900 | M10: =L10*Parametros!$B$5+IF(L10>=Parametros!$B$8,0,IF(L10>=Parametros!$B$7,Parametros!$B$11,IF(L10>=Parametros!$B$6,Parametros!$B$10,Parametros!$B$9))) | N10: 0 | O10: =L10*Parametros!$B$13 | P10: =L10-M10-N10-O10 | Q10: =P10/(1+Parametros!$B$4) | R10: =Q10-H10 | S10: =IF(H10=0,0,R10/H10) | T10: =IF(L10<Parametros!$B$8,"PAGA COSTO FIJO",IF(S10>=I10,"OK","AJUSTAR")) | U10: =L10/(1+Parametros!$B$4)/G10 | V10: =IF(E10=0,0,U10/E10-1) | W10: Formato chico (envío a cargo del comprador)
A11: 924 | B11: EP1011 | C11: Film Stretch Manual Negro Con Mango 50 Cm 2.8 Kg | D11: 3007 | E11: 4791 | F11: 0 | G11: 11.2 | H11: =D11*G11 | I11: =Parametros!$B$14 | J11: =((1+Parametros!$B$4)*H11*(1+I11)+Parametros!$B$12)/(1-Parametros!$B$5-Parametros!$B$13) | K11: =((1+Parametros!$B$4)*H11*(1+I11)+Parametros!$B$12+IF(J11>=Parametros!$B$8,0,IF(J11>=Parametros!$B$7,Parametros!$B$11,IF(J11>=Parametros!$B$6,Parametros!$B$10,Parametros!$B$9))))/(1-Parametros!$B$5-Parametros!$B$13) | L11: 17900 | M11: =L11*Parametros!$B$5+IF(L11>=Parametros!$B$8,0,IF(L11>=Parametros!$B$7,Parametros!$B$11,IF(L11>=Parametros!$B$6,Parametros!$B$10,Parametros!$B$9))) | N11: 0 | O11: =L11*Parametros!$B$13 | P11: =L11-M11-N11-O11 | Q11: =P11/(1+Parametros!$B$4) | R11: =Q11-H11 | S11: =IF(H11=0,0,R11/H11) | T11: =IF(L11<Parametros!$B$8,"PAGA COSTO FIJO",IF(S11>=I11,"OK","AJUSTAR")) | U11: =L11/(1+Parametros!$B$4)/G11 | V11: =IF(E11=0,0,U11/E11-1) | W11: Formato chico (envío a cargo del comprador)
A12: 925 | B12: EP1013 | C12: Film Stretch Manual Negro Con Mango 50 Cm 4 Kg | D12: 3260 | E12: 5199 | F12: 0 | G12: 16 | H12: =D12*G12 | I12: =Parametros!$B$14 | J12: =((1+Parametros!$B$4)*H12*(1+I12)+Parametros!$B$12)/(1-Parametros!$B$5-Parametros!$B$13) | K12: =((1+Parametros!$B$4)*H12*(1+I12)+Parametros!$B$12+IF(J12>=Parametros!$B$8,0,IF(J12>=Parametros!$B$7,Parametros!$B$11,IF(J12>=Parametros!$B$6,Parametros!$B$10,Parametros!$B$9))))/(1-Parametros!$B$5-Parametros!$B$13) | L12: 25900 | M12: =L12*Parametros!$B$5+IF(L12>=Parametros!$B$8,0,IF(L12>=Parametros!$B$7,Parametros!$B$11,IF(L12>=Parametros!$B$6,Parametros!$B$10,Parametros!$B$9))) | N12: 0 | O12: =L12*Parametros!$B$13 | P12: =L12-M12-N12-O12 | Q12: =P12/(1+Parametros!$B$4) | R12: =Q12-H12 | S12: =IF(H12=0,0,R12/H12) | T12: =IF(L12<Parametros!$B$8,"PAGA COSTO FIJO",IF(S12>=I12,"OK","AJUSTAR")) | U12: =L12/(1+Parametros!$B$4)/G12 | V12: =IF(E12=0,0,U12/E12-1) | W12: Formato chico (envío a cargo del comprador)
A13: 981 | B13: EP1076 | C13: Film Stretch Manual Negro Sin Mango 50 Cm 3.5 Kg | D13: 2009 | E13: 3189 | F13: 0 | G13: 14 | H13: =D13*G13 | I13: =Parametros!$B$14 | J13: =((1+Parametros!$B$4)*H13*(1+I13)+Parametros!$B$12)/(1-Parametros!$B$5-Parametros!$B$13) | K13: =((1+Parametros!$B$4)*H13*(1+I13)+Parametros!$B$12+IF(J13>=Parametros!$B$8,0,IF(J13>=Parametros!$B$7,Parametros!$B$11,IF(J13>=Parametros!$B$6,Parametros!$B$10,Parametros!$B$9))))/(1-Parametros!$B$5-Parametros!$B$13) | L13: 85000 | M13: =L13*Parametros!$B$5+IF(L13>=Parametros!$B$8,0,IF(L13>=Parametros!$B$7,Parametros!$B$11,IF(L13>=Parametros!$B$6,Parametros!$B$10,Parametros!$B$9))) | N13: 29860 | O13: =L13*Parametros!$B$13 | P13: =L13-M13-N13-O13 | Q13: =P13/(1+Parametros!$B$4) | R13: =Q13-H13 | S13: =IF(H13=0,0,R13/H13) | T13: =IF(L13<Parametros!$B$8,"PAGA COSTO FIJO",IF(S13>=I13,"OK","AJUSTAR")) | U13: =L13/(1+Parametros!$B$4)/G13 | V13: =IF(E13=0,0,U13/E13-1) | W13: BANDERA (envío gratis)
A14: 968 | B14: EP1055 | C14: Film Stretch Manual Negro Sin Mango 50 Cm 4.5 Kg | D14: 2346 | E14: 3751 | F14: 0 | G14: 18 | H14: =D14*G14 | I14: =Parametros!$B$14 | J14: =((1+Parametros!$B$4)*H14*(1+I14)+Parametros!$B$12)/(1-Parametros!$B$5-Parametros!$B$13) | K14: =((1+Parametros!$B$4)*H14*(1+I14)+Parametros!$B$12+IF(J14>=Parametros!$B$8,0,IF(J14>=Parametros!$B$7,Parametros!$B$11,IF(J14>=Parametros!$B$6,Parametros!$B$10,Parametros!$B$9))))/(1-Parametros!$B$5-Parametros!$B$13) | L14: 26900 | M14: =L14*Parametros!$B$5+IF(L14>=Parametros!$B$8,0,IF(L14>=Parametros!$B$7,Parametros!$B$11,IF(L14>=Parametros!$B$6,Parametros!$B$10,Parametros!$B$9))) | N14: 0 | O14: =L14*Parametros!$B$13 | P14: =L14-M14-N14-O14 | Q14: =P14/(1+Parametros!$B$4) | R14: =Q14-H14 | S14: =IF(H14=0,0,R14/H14) | T14: =IF(L14<Parametros!$B$8,"PAGA COSTO FIJO",IF(S14>=I14,"OK","AJUSTAR")) | U14: =L14/(1+Parametros!$B$4)/G14 | V14: =IF(E14=0,0,U14/E14-1) | W14: Formato chico (envío a cargo del comprador)
A15: 926 | B15: EP1058 | C15: Film Stretch Manual Negro Sin Mango 50 Cm 5 Kg | D15: 2670 | E15: 4243 | F15: 0 | G15: 20 | H15: =D15*G15 | I15: =Parametros!$B$14 | J15: =((1+Parametros!$B$4)*H15*(1+I15)+Parametros!$B$12)/(1-Parametros!$B$5-Parametros!$B$13) | K15: =((1+Parametros!$B$4)*H15*(1+I15)+Parametros!$B$12+IF(J15>=Parametros!$B$8,0,IF(J15>=Parametros!$B$7,Parametros!$B$11,IF(J15>=Parametros!$B$6,Parametros!$B$10,Parametros!$B$9))))/(1-Parametros!$B$5-Parametros!$B$13) | L15: 29900 | M15: =L15*Parametros!$B$5+IF(L15>=Parametros!$B$8,0,IF(L15>=Parametros!$B$7,Parametros!$B$11,IF(L15>=Parametros!$B$6,Parametros!$B$10,Parametros!$B$9))) | N15: 0 | O15: =L15*Parametros!$B$13 | P15: =L15-M15-N15-O15 | Q15: =P15/(1+Parametros!$B$4) | R15: =Q15-H15 | S15: =IF(H15=0,0,R15/H15) | T15: =IF(L15<Parametros!$B$8,"PAGA COSTO FIJO",IF(S15>=I15,"OK","AJUSTAR")) | U15: =L15/(1+Parametros!$B$4)/G15 | V15: =IF(E15=0,0,U15/E15-1) | W15: Formato chico (envío a cargo del comprador)
A16: 927 | B16: EP1008 | C16: Film Stretch Manual Transparente 10 Cm 0.5 Kg x Unidad | D16: 1574 | E16: 2993 | F16: 0 | G16: 25 | H16: =D16*G16 | I16: =Parametros!$B$14 | J16: =((1+Parametros!$B$4)*H16*(1+I16)+Parametros!$B$12)/(1-Parametros!$B$5-Parametros!$B$13) | K16: =((1+Parametros!$B$4)*H16*(1+I16)+Parametros!$B$12+IF(J16>=Parametros!$B$8,0,IF(J16>=Parametros!$B$7,Parametros!$B$11,IF(J16>=Parametros!$B$6,Parametros!$B$10,Parametros!$B$9))))/(1-Parametros!$B$5-Parametros!$B$13) | L16: 36900 | M16: =L16*Parametros!$B$5+IF(L16>=Parametros!$B$8,0,IF(L16>=Parametros!$B$7,Parametros!$B$11,IF(L16>=Parametros!$B$6,Parametros!$B$10,Parametros!$B$9))) | N16: 0 | O16: =L16*Parametros!$B$13 | P16: =L16-M16-N16-O16 | Q16: =P16/(1+Parametros!$B$4) | R16: =Q16-H16 | S16: =IF(H16=0,0,R16/H16) | T16: =IF(L16<Parametros!$B$8,"PAGA COSTO FIJO",IF(S16>=I16,"OK","AJUSTAR")) | U16: =L16/(1+Parametros!$B$4)/G16 | V16: =IF(E16=0,0,U16/E16-1) | W16: Formato chico (envío a cargo del comprador)
A17: 928 | B17: EP1003 | C17: Film Stretch Manual Transparente Con Mango 50 Cm 2.8 Kg | D17: 2782 | E17: 4440 | F17: 0 | G17: 11.2 | H17: =D17*G17 | I17: =Parametros!$B$14 | J17: =((1+Parametros!$B$4)*H17*(1+I17)+Parametros!$B$12)/(1-Parametros!$B$5-Parametros!$B$13) | K17: =((1+Parametros!$B$4)*H17*(1+I17)+Parametros!$B$12+IF(J17>=Parametros!$B$8,0,IF(J17>=Parametros!$B$7,Parametros!$B$11,IF(J17>=Parametros!$B$6,Parametros!$B$10,Parametros!$B$9))))/(1-Parametros!$B$5-Parametros!$B$13) | L17: 17500 | M17: =L17*Parametros!$B$5+IF(L17>=Parametros!$B$8,0,IF(L17>=Parametros!$B$7,Parametros!$B$11,IF(L17>=Parametros!$B$6,Parametros!$B$10,Parametros!$B$9))) | N17: 0 | O17: =L17*Parametros!$B$13 | P17: =L17-M17-N17-O17 | Q17: =P17/(1+Parametros!$B$4) | R17: =Q17-H17 | S17: =IF(H17=0,0,R17/H17) | T17: =IF(L17<Parametros!$B$8,"PAGA COSTO FIJO",IF(S17>=I17,"OK","AJUSTAR")) | U17: =L17/(1+Parametros!$B$4)/G17 | V17: =IF(E17=0,0,U17/E17-1) | W17: Formato chico (envío a cargo del comprador)
A18: 879 | B18: EP1005 | C18: Film Stretch Manual Transparente Con Mango 50 Cm 4 Kg | D18: 3021 | E18: 4819 | F18: 0 | G18: 16 | H18: =D18*G18 | I18: =Parametros!$B$14 | J18: =((1+Parametros!$B$4)*H18*(1+I18)+Parametros!$B$12)/(1-Parametros!$B$5-Parametros!$B$13) | K18: =((1+Parametros!$B$4)*H18*(1+I18)+Parametros!$B$12+IF(J18>=Parametros!$B$8,0,IF(J18>=Parametros!$B$7,Parametros!$B$11,IF(J18>=Parametros!$B$6,Parametros!$B$10,Parametros!$B$9))))/(1-Parametros!$B$5-Parametros!$B$13) | L18: 24900 | M18: =L18*Parametros!$B$5+IF(L18>=Parametros!$B$8,0,IF(L18>=Parametros!$B$7,Parametros!$B$11,IF(L18>=Parametros!$B$6,Parametros!$B$10,Parametros!$B$9))) | N18: 0 | O18: =L18*Parametros!$B$13 | P18: =L18-M18-N18-O18 | Q18: =P18/(1+Parametros!$B$4) | R18: =Q18-H18 | S18: =IF(H18=0,0,R18/H18) | T18: =IF(L18<Parametros!$B$8,"PAGA COSTO FIJO",IF(S18>=I18,"OK","AJUSTAR")) | U18: =L18/(1+Parametros!$B$4)/G18 | V18: =IF(E18=0,0,U18/E18-1) | W18: Formato chico (envío a cargo del comprador)
... A22: 929 | B22: EP1076 | C22: Film Stretch Manual Transparente Sin Mango 50 Cm 3.5 Kg | D22: 2009 | E22: 3189 | F22: 0 | G22: 14 | H22: =D22*G22 | I22: =Parametros!$B$14 | J22: =((1+Parametros!$B$4)*H22*(1+I22)+Parametros!$B$12)/(1-Parametros!$B$5-Parametros!$B$13) | K22: =((1+Parametros!$B$4)*H22*(1+I22)+Parametros!$B$12+IF(J22>=Parametros!$B$8,0,IF(J22>=Parametros!$B$7,Parametros!$B$11,IF(J22>=Parametros!$B$6,Parametros!$B$10,Parametros!$B$9))))/(1-Parametros!$B$5-Parametros!$B$13) | L22: 81000 | M22: =L22*Parametros!$B$5+IF(L22>=Parametros!$B$8,0,IF(L22>=Parametros!$B$7,Parametros!$B$11,IF(L22>=Parametros!$B$6,Parametros!$B$10,Parametros!$B$9))) | N22: 29860 | O22: =L22*Parametros!$B$13 | P22: =L22-M22-N22-O22 | Q22: =P22/(1+Parametros!$B$4) | R22: =Q22-H22 | S22: =IF(H22=0,0,R22/H22) | T22: =IF(L22<Parametros!$B$8,"PAGA COSTO FIJO",IF(S22>=I22,"OK","AJUSTAR")) | U22: =L22/(1+Parametros!$B$4)/G22 | V22: =IF(E22=0,0,U22/E22-1) | W22: BANDERA (envío gratis)

Sheet Comisiones ML (datos)
A1: Comisiones reales — API ML 16-jul-2026 (MLA405117, Clásica/gold_special)
A2: GET /sites/MLA/listing_prices?price=X&listing_type_id=gold_special&category_id=MLA405117
A4: Precio final $ | B4: Comisión % ($) | C4: Costo fijo $ | D4: Fee total $
A5: 2000 | B5: 306.42 | C5: 1250 | D5: 1556.42
A6: 5000 | B6: 766.04 | C6: 1250 | D6: 2016.04
A7: 10000 | B7: 1532.08 | C7: 1250 | D7: 2782.08
A8: 15000 | B8: 2298.13 | C8: 1250 | D8: 3548.13
A9: 20000 | B9: 3064.17 | C9: 2505 | D9: 5569.17
A10: 30000 | B10: 4596.26 | C10: 3005 | D10: 7601.26
A11: 40000 | B11: 6128.34 | C11: 0 | D11: 6128.34
A12: 60000 | B12: 9192.51 | C12: 0 | D12: 9192.51
A13: 80000 | B13: 12256.68 | C13: 0 | D13: 12256.68
A14: 120000 | B14: 18385.02 | C14: 0 | D14: 18385.02
A16: Comisión porcentual constante: 15,32085%. El costo fijo desaparece a partir de $40.000.
A17: OJO: ML actualiza estos valores varias veces al año. Ante dudas, re-consultar la API o el simulador de ML.
